{
  "ticker": "DSY.PA",
  "best": "S1_FAST",
  "decision_window": "2Y",
  "params": {
    "golden_min_weeks_on": 4,
    "golden_trailing_atr_mult": 1.0
  },
  "cums": {
    "S0_BASE": -26.42,
    "S1_FAST": -17.83,
    "S2_HOLD12": -26.42,
    "S3_HOLD16": -26.42,
    "S4_WIDEATR": -26.42,
    "S5_COMBO": -26.42,
    "S6_TIGHT": -17.83,
    "S2_HOLD12_BUF": -26.42,
    "S3_HOLD16_BUF": -26.42,
    "S5_COMBO_BUF": -26.42,
    "S8_DI_GUARD": -19.9,
    "S8_DI_GUARD_BUF": -19.9,
    "S11_VOLATILE_FAST": -17.83,
    "S12_COMPOUNDER_HOLD": -26.42,
    "S12_RECOVERY": -24.13
  },
  "cums_full": {
    "S0_BASE": 98.52,
    "S1_FAST": 96.2,
    "S2_HOLD12": 88.95,
    "S3_HOLD16": 159.95,
    "S4_WIDEATR": 109.02,
    "S5_COMBO": 85.42,
    "S6_TIGHT": 96.2,
    "S2_HOLD12_BUF": 114.19,
    "S3_HOLD16_BUF": 150.0,
    "S5_COMBO_BUF": 110.56,
    "S8_DI_GUARD": 90.23,
    "S8_DI_GUARD_BUF": 74.08,
    "S11_VOLATILE_FAST": 87.1,
    "S12_COMPOUNDER_HOLD": 108.09,
    "S12_RECOVERY": 68.46
  },
  "cums_4y": {
    "S0_BASE": -35.88,
    "S1_FAST": -31.86,
    "S2_HOLD12": -41.11,
    "S3_HOLD16": -41.11,
    "S4_WIDEATR": -38.85,
    "S5_COMBO": -42.01,
    "S6_TIGHT": -31.86,
    "S2_HOLD12_BUF": -41.11,
    "S3_HOLD16_BUF": -41.11,
    "S5_COMBO_BUF": -42.01,
    "S8_DI_GUARD": -33.57,
    "S8_DI_GUARD_BUF": -38.98,
    "S11_VOLATILE_FAST": -27.22,
    "S12_COMPOUNDER_HOLD": -36.15,
    "S12_RECOVERY": -35.7
  },
  "cums_3y": {
    "S0_BASE": -22.67,
    "S1_FAST": -17.82,
    "S2_HOLD12": -28.97,
    "S3_HOLD16": -28.97,
    "S4_WIDEATR": -26.25,
    "S5_COMBO": -30.06,
    "S6_TIGHT": -17.82,
    "S2_HOLD12_BUF": -28.97,
    "S3_HOLD16_BUF": -28.97,
    "S5_COMBO_BUF": -30.06,
    "S8_DI_GUARD": -19.89,
    "S8_DI_GUARD_BUF": -26.41,
    "S11_VOLATILE_FAST": -10.05,
    "S12_COMPOUNDER_HOLD": -23.0,
    "S12_RECOVERY": -30.09
  },
  "cums_2y": {
    "S0_BASE": -26.42,
    "S1_FAST": -17.83,
    "S2_HOLD12": -26.42,
    "S3_HOLD16": -26.42,
    "S4_WIDEATR": -26.42,
    "S5_COMBO": -26.42,
    "S6_TIGHT": -17.83,
    "S2_HOLD12_BUF": -26.42,
    "S3_HOLD16_BUF": -26.42,
    "S5_COMBO_BUF": -26.42,
    "S8_DI_GUARD": -19.9,
    "S8_DI_GUARD_BUF": -19.9,
    "S11_VOLATILE_FAST": -17.83,
    "S12_COMPOUNDER_HOLD": -26.42,
    "S12_RECOVERY": -24.13
  },
  "cums_1y": {
    "S0_BASE": -22.18,
    "S1_FAST": -18.79,
    "S2_HOLD12": -22.18,
    "S3_HOLD16": -22.18,
    "S4_WIDEATR": -22.18,
    "S5_COMBO": -22.18,
    "S6_TIGHT": -18.79,
    "S2_HOLD12_BUF": -22.18,
    "S3_HOLD16_BUF": -22.18,
    "S5_COMBO_BUF": -22.18,
    "S8_DI_GUARD": -20.3,
    "S8_DI_GUARD_BUF": -20.3,
    "S11_VOLATILE_FAST": -18.79,
    "S12_COMPOUNDER_HOLD": -22.18,
    "S12_RECOVERY": -22.18
  },
  "best_full": "S3_HOLD16",
  "best_4y": "S11_VOLATILE_FAST",
  "best_3y": "S11_VOLATILE_FAST",
  "computed": "2026-04-07T11:39:59",
  "cache_version": "2026-04-07-v4",
  "fingerprint": "880b45a717fadda1d695ba02c2f91767119140e877aa0ac01fcf0d9f578645af"
}