{
  "ticker": "FISV",
  "best": "S8_DI_GUARD_BUF",
  "decision_window": "2Y",
  "params": {
    "golden_min_weeks_on": 4,
    "golden_trailing_atr_mult": 1.0,
    "silver_require_bullish_di": true,
    "golden_rsi_entry_buffer": 30.0,
    "golden_rsi_high_quantile": 0.92
  },
  "cums": {
    "S0_BASE": 34.2,
    "S1_FAST": 40.5,
    "S2_HOLD12": 34.2,
    "S3_HOLD16": 34.2,
    "S4_WIDEATR": 20.02,
    "S5_COMBO": 20.02,
    "S6_TIGHT": 42.53,
    "S2_HOLD12_BUF": 34.2,
    "S3_HOLD16_BUF": 34.2,
    "S5_COMBO_BUF": 18.81,
    "S8_DI_GUARD": 47.55,
    "S8_DI_GUARD_BUF": 49.68,
    "S11_VOLATILE_FAST": 48.95,
    "S12_COMPOUNDER_HOLD": 34.2,
    "S12_RECOVERY": 18.81
  },
  "cums_full": {
    "S0_BASE": 1750.36,
    "S1_FAST": 2549.36,
    "S2_HOLD12": 1794.38,
    "S3_HOLD16": 1840.39,
    "S4_WIDEATR": 1534.7,
    "S5_COMBO": 1578.68,
    "S6_TIGHT": 2683.45,
    "S2_HOLD12_BUF": 2230.8,
    "S3_HOLD16_BUF": 2278.25,
    "S5_COMBO_BUF": 1802.71,
    "S8_DI_GUARD": 2554.64,
    "S8_DI_GUARD_BUF": 3101.1,
    "S11_VOLATILE_FAST": 2688.49,
    "S12_COMPOUNDER_HOLD": 1781.66,
    "S12_RECOVERY": 780.78
  },
  "cums_4y": {
    "S0_BASE": 123.82,
    "S1_FAST": 153.99,
    "S2_HOLD12": 135.0,
    "S3_HOLD16": 135.0,
    "S4_WIDEATR": 110.68,
    "S5_COMBO": 114.75,
    "S6_TIGHT": 157.65,
    "S2_HOLD12_BUF": 150.81,
    "S3_HOLD16_BUF": 150.81,
    "S5_COMBO_BUF": 112.58,
    "S8_DI_GUARD": 172.98,
    "S8_DI_GUARD_BUF": 182.9,
    "S11_VOLATILE_FAST": 169.26,
    "S12_COMPOUNDER_HOLD": 129.55,
    "S12_RECOVERY": 74.27
  },
  "cums_3y": {
    "S0_BASE": 89.76,
    "S1_FAST": 120.62,
    "S2_HOLD12": 116.28,
    "S3_HOLD16": 116.28,
    "S4_WIDEATR": 78.62,
    "S5_COMBO": 78.62,
    "S6_TIGHT": 123.81,
    "S2_HOLD12_BUF": 130.83,
    "S3_HOLD16_BUF": 130.83,
    "S5_COMBO_BUF": 76.82,
    "S8_DI_GUARD": 128.79,
    "S8_DI_GUARD_BUF": 137.09,
    "S11_VOLATILE_FAST": 133.88,
    "S12_COMPOUNDER_HOLD": 90.93,
    "S12_RECOVERY": 71.44
  },
  "cums_2y": {
    "S0_BASE": 34.2,
    "S1_FAST": 40.5,
    "S2_HOLD12": 34.2,
    "S3_HOLD16": 34.2,
    "S4_WIDEATR": 20.02,
    "S5_COMBO": 20.02,
    "S6_TIGHT": 42.53,
    "S2_HOLD12_BUF": 34.2,
    "S3_HOLD16_BUF": 34.2,
    "S5_COMBO_BUF": 18.81,
    "S8_DI_GUARD": 47.55,
    "S8_DI_GUARD_BUF": 49.68,
    "S11_VOLATILE_FAST": 48.95,
    "S12_COMPOUNDER_HOLD": 34.2,
    "S12_RECOVERY": 18.81
  },
  "cums_1y": {
    "S0_BASE": -13.12,
    "S1_FAST": -7.73,
    "S2_HOLD12": -13.12,
    "S3_HOLD16": -13.12,
    "S4_WIDEATR": -13.12,
    "S5_COMBO": -13.12,
    "S6_TIGHT": -7.73,
    "S2_HOLD12_BUF": -13.12,
    "S3_HOLD16_BUF": -13.12,
    "S5_COMBO_BUF": -13.12,
    "S8_DI_GUARD": -3.1,
    "S8_DI_GUARD_BUF": -3.1,
    "S11_VOLATILE_FAST": -2.18,
    "S12_COMPOUNDER_HOLD": -13.12,
    "S12_RECOVERY": -13.12
  },
  "best_full": "S8_DI_GUARD_BUF",
  "best_4y": "S8_DI_GUARD_BUF",
  "best_3y": "S8_DI_GUARD_BUF",
  "computed": "2026-04-08T13:42:04",
  "cache_version": "2026-04-07-v4",
  "fingerprint": "880b45a717fadda1d695ba02c2f91767119140e877aa0ac01fcf0d9f578645af"
}