{
  "ticker": "HEN3.DE",
  "best": "S2_HOLD12",
  "decision_window": "2Y",
  "params": {
    "golden_min_weeks_on": 12
  },
  "cums": {
    "S0_BASE": -11.37,
    "S1_FAST": -11.37,
    "S2_HOLD12": 1.01,
    "S3_HOLD16": 1.01,
    "S4_WIDEATR": -8.26,
    "S5_COMBO": -0.9,
    "S6_TIGHT": -11.37,
    "S2_HOLD12_BUF": 0.89,
    "S3_HOLD16_BUF": 0.89,
    "S5_COMBO_BUF": -1.02,
    "S8_DI_GUARD": -14.97,
    "S8_DI_GUARD_BUF": -9.74,
    "S11_VOLATILE_FAST": -3.01,
    "S12_COMPOUNDER_HOLD": -11.39,
    "S12_RECOVERY": -13.93
  },
  "cums_full": {
    "S0_BASE": 66.21,
    "S1_FAST": 44.71,
    "S2_HOLD12": 51.88,
    "S3_HOLD16": 62.69,
    "S4_WIDEATR": 80.51,
    "S5_COMBO": 24.82,
    "S6_TIGHT": 57.72,
    "S2_HOLD12_BUF": 33.87,
    "S3_HOLD16_BUF": 32.86,
    "S5_COMBO_BUF": 8.34,
    "S8_DI_GUARD": 52.01,
    "S8_DI_GUARD_BUF": 72.04,
    "S11_VOLATILE_FAST": 78.22,
    "S12_COMPOUNDER_HOLD": 56.17,
    "S12_RECOVERY": 17.34
  },
  "cums_4y": {
    "S0_BASE": 5.23,
    "S1_FAST": -2.47,
    "S2_HOLD12": 7.42,
    "S3_HOLD16": 7.42,
    "S4_WIDEATR": 8.91,
    "S5_COMBO": 2.43,
    "S6_TIGHT": -2.31,
    "S2_HOLD12_BUF": 7.29,
    "S3_HOLD16_BUF": 7.29,
    "S5_COMBO_BUF": -1.05,
    "S8_DI_GUARD": -3.12,
    "S8_DI_GUARD_BUF": 3.23,
    "S11_VOLATILE_FAST": 6.82,
    "S12_COMPOUNDER_HOLD": -2.85,
    "S12_RECOVERY": -14.83
  },
  "cums_3y": {
    "S0_BASE": 2.13,
    "S1_FAST": -1.86,
    "S2_HOLD12": 8.6,
    "S3_HOLD16": 8.6,
    "S4_WIDEATR": 5.71,
    "S5_COMBO": -0.3,
    "S6_TIGHT": -1.7,
    "S2_HOLD12_BUF": 8.47,
    "S3_HOLD16_BUF": 8.47,
    "S5_COMBO_BUF": -7.21,
    "S8_DI_GUARD": -5.85,
    "S8_DI_GUARD_BUF": 0.1,
    "S11_VOLATILE_FAST": 7.48,
    "S12_COMPOUNDER_HOLD": -1.78,
    "S12_RECOVERY": -4.59
  },
  "cums_2y": {
    "S0_BASE": -11.37,
    "S1_FAST": -11.37,
    "S2_HOLD12": 1.01,
    "S3_HOLD16": 1.01,
    "S4_WIDEATR": -8.26,
    "S5_COMBO": -0.9,
    "S6_TIGHT": -11.37,
    "S2_HOLD12_BUF": 0.89,
    "S3_HOLD16_BUF": 0.89,
    "S5_COMBO_BUF": -1.02,
    "S8_DI_GUARD": -14.97,
    "S8_DI_GUARD_BUF": -9.74,
    "S11_VOLATILE_FAST": -3.01,
    "S12_COMPOUNDER_HOLD": -11.39,
    "S12_RECOVERY": -13.93
  },
  "cums_1y": {
    "S0_BASE": 0.2,
    "S1_FAST": 0.2,
    "S2_HOLD12": 0.2,
    "S3_HOLD16": 0.2,
    "S4_WIDEATR": 0.2,
    "S5_COMBO": 0.17,
    "S6_TIGHT": 0.2,
    "S2_HOLD12_BUF": 0.2,
    "S3_HOLD16_BUF": 0.2,
    "S5_COMBO_BUF": 0.17,
    "S8_DI_GUARD": -3.87,
    "S8_DI_GUARD_BUF": -3.87,
    "S11_VOLATILE_FAST": 0.2,
    "S12_COMPOUNDER_HOLD": 0.17,
    "S12_RECOVERY": -11.14
  },
  "best_full": "S4_WIDEATR",
  "best_4y": "S4_WIDEATR",
  "best_3y": "S2_HOLD12",
  "computed": "2026-04-07T11:43:42",
  "cache_version": "2026-04-07-v4",
  "fingerprint": "880b45a717fadda1d695ba02c2f91767119140e877aa0ac01fcf0d9f578645af"
}