{
  "ticker": "ORCL",
  "best": "S1_FAST",
  "decision_window": "4Y",
  "params": {
    "golden_min_weeks_on": 4,
    "golden_trailing_atr_mult": 1.0
  },
  "cums": {
    "S0_BASE": 72.76,
    "S1_FAST": 88.52,
    "S2_HOLD12": 75.71,
    "S3_HOLD16": 64.82,
    "S4_WIDEATR": 83.25,
    "S5_COMBO": 86.09,
    "S6_TIGHT": 88.52,
    "S2_HOLD12_BUF": 50.4,
    "S3_HOLD16_BUF": 60.47,
    "S5_COMBO_BUF": 81.61,
    "S8_DI_GUARD": 88.52,
    "S8_DI_GUARD_BUF": 38.07,
    "S11_VOLATILE_FAST": 80.54,
    "S12_COMPOUNDER_HOLD": 78.18,
    "S12_RECOVERY": 51.93
  },
  "cums_full": {
    "S0_BASE": 92.61,
    "S1_FAST": 98.23,
    "S2_HOLD12": 88.68,
    "S3_HOLD16": 113.13,
    "S4_WIDEATR": 182.92,
    "S5_COMBO": 155.31,
    "S6_TIGHT": 81.58,
    "S2_HOLD12_BUF": 81.31,
    "S3_HOLD16_BUF": 104.75,
    "S5_COMBO_BUF": 144.9,
    "S8_DI_GUARD": 93.75,
    "S8_DI_GUARD_BUF": 45.94,
    "S11_VOLATILE_FAST": 102.91,
    "S12_COMPOUNDER_HOLD": 85.08,
    "S12_RECOVERY": 24.56
  },
  "cums_4y": {
    "S0_BASE": 72.76,
    "S1_FAST": 88.52,
    "S2_HOLD12": 75.71,
    "S3_HOLD16": 64.82,
    "S4_WIDEATR": 83.25,
    "S5_COMBO": 86.09,
    "S6_TIGHT": 88.52,
    "S2_HOLD12_BUF": 50.4,
    "S3_HOLD16_BUF": 60.47,
    "S5_COMBO_BUF": 81.61,
    "S8_DI_GUARD": 88.52,
    "S8_DI_GUARD_BUF": 38.07,
    "S11_VOLATILE_FAST": 80.54,
    "S12_COMPOUNDER_HOLD": 78.18,
    "S12_RECOVERY": 51.93
  },
  "cums_3y": {
    "S0_BASE": null,
    "S1_FAST": null,
    "S2_HOLD12": null,
    "S3_HOLD16": null,
    "S4_WIDEATR": null,
    "S5_COMBO": null,
    "S6_TIGHT": null,
    "S2_HOLD12_BUF": 19.35,
    "S3_HOLD16_BUF": 19.35,
    "S5_COMBO_BUF": 43.84,
    "S8_DI_GUARD": null,
    "S8_DI_GUARD_BUF": 11.86,
    "S11_VOLATILE_FAST": null,
    "S12_COMPOUNDER_HOLD": null,
    "S12_RECOVERY": 20.31
  },
  "best_full": "S4_WIDEATR",
  "best_4y": "S1_FAST",
  "best_3y": "S5_COMBO_BUF",
  "computed": "2026-04-06T16:19:54",
  "cache_version": "2026-04-05-v2",
  "fingerprint": "5cb4f56670a815b0e15f22e315f447fe116c1d9e81211cf6e66a7eba27eab546"
}