{
  "ticker": "PUIG.MC",
  "best": "S0_BASE",
  "decision_window": "2Y",
  "params": {},
  "cums": {
    "S0_BASE": null,
    "S1_FAST": null,
    "S2_HOLD12": null,
    "S3_HOLD16": null,
    "S4_WIDEATR": null,
    "S5_COMBO": null,
    "S6_TIGHT": null,
    "S2_HOLD12_BUF": null,
    "S3_HOLD16_BUF": null,
    "S5_COMBO_BUF": null,
    "S8_DI_GUARD": null,
    "S8_DI_GUARD_BUF": null,
    "S11_VOLATILE_FAST": null,
    "S12_COMPOUNDER_HOLD": null,
    "S12_RECOVERY": null,
    "S13_QUALITY_HOLD": null
  },
  "cums_full": {
    "S0_BASE": null,
    "S1_FAST": null,
    "S2_HOLD12": null,
    "S3_HOLD16": null,
    "S4_WIDEATR": null,
    "S5_COMBO": null,
    "S6_TIGHT": null,
    "S2_HOLD12_BUF": null,
    "S3_HOLD16_BUF": null,
    "S5_COMBO_BUF": null,
    "S8_DI_GUARD": null,
    "S8_DI_GUARD_BUF": null,
    "S11_VOLATILE_FAST": null,
    "S12_COMPOUNDER_HOLD": null,
    "S12_RECOVERY": null,
    "S13_QUALITY_HOLD": null
  },
  "cums_4y": {
    "S0_BASE": null,
    "S1_FAST": null,
    "S2_HOLD12": null,
    "S3_HOLD16": null,
    "S4_WIDEATR": null,
    "S5_COMBO": null,
    "S6_TIGHT": null,
    "S2_HOLD12_BUF": null,
    "S3_HOLD16_BUF": null,
    "S5_COMBO_BUF": null,
    "S8_DI_GUARD": null,
    "S8_DI_GUARD_BUF": null,
    "S11_VOLATILE_FAST": null,
    "S12_COMPOUNDER_HOLD": null,
    "S12_RECOVERY": null,
    "S13_QUALITY_HOLD": null
  },
  "cums_3y": {
    "S0_BASE": null,
    "S1_FAST": null,
    "S2_HOLD12": null,
    "S3_HOLD16": null,
    "S4_WIDEATR": null,
    "S5_COMBO": null,
    "S6_TIGHT": null,
    "S2_HOLD12_BUF": null,
    "S3_HOLD16_BUF": null,
    "S5_COMBO_BUF": null,
    "S8_DI_GUARD": null,
    "S8_DI_GUARD_BUF": null,
    "S11_VOLATILE_FAST": null,
    "S12_COMPOUNDER_HOLD": null,
    "S12_RECOVERY": null,
    "S13_QUALITY_HOLD": null
  },
  "cums_2y": {
    "S0_BASE": null,
    "S1_FAST": null,
    "S2_HOLD12": null,
    "S3_HOLD16": null,
    "S4_WIDEATR": null,
    "S5_COMBO": null,
    "S6_TIGHT": null,
    "S2_HOLD12_BUF": null,
    "S3_HOLD16_BUF": null,
    "S5_COMBO_BUF": null,
    "S8_DI_GUARD": null,
    "S8_DI_GUARD_BUF": null,
    "S11_VOLATILE_FAST": null,
    "S12_COMPOUNDER_HOLD": null,
    "S12_RECOVERY": null,
    "S13_QUALITY_HOLD": null
  },
  "cums_1y": {
    "S0_BASE": null,
    "S1_FAST": null,
    "S2_HOLD12": null,
    "S3_HOLD16": null,
    "S4_WIDEATR": null,
    "S5_COMBO": null,
    "S6_TIGHT": null,
    "S2_HOLD12_BUF": null,
    "S3_HOLD16_BUF": null,
    "S5_COMBO_BUF": null,
    "S8_DI_GUARD": null,
    "S8_DI_GUARD_BUF": null,
    "S11_VOLATILE_FAST": null,
    "S12_COMPOUNDER_HOLD": null,
    "S12_RECOVERY": null,
    "S13_QUALITY_HOLD": null
  },
  "best_full": "S0_BASE",
  "best_4y": "S0_BASE",
  "best_3y": "S0_BASE",
  "computed": "2026-04-11T06:45:23",
  "cache_version": "2026-04-07-v4",
  "fingerprint": "d1b737a2e1d393d6d2a343ce332ccb44b12011b8eaf98e4280f9fe5b24565678"
}